<?xml version="1.0" ?>
<annotation>
	<folder>bdd100k</folder>
	<filename>0df9627b-d2726822.jpg</filename>
	<source>
		<database>voc_bdd</database>
		<annotation>bdd100k</annotation>
		<image>flickr</image>
		<flickrid>NULL</flickrid>
	</source>
	<owner>
		<flickrid>NULL</flickrid>
		<name>lijing</name>
	</owner>
	<size>
		<width>1280</width>
		<height>720</height>
		<depth>3</depth>
	</size>
	<segmented>0</segmented>
	<object>
		<name>car</name>
		<pose>Unspecified</pose>
		<truncated>0</truncated>
		<difficult>0</difficult>
		<bndbox>
			<xmin>539</xmin>
			<ymin>366</ymin>
			<xmax>615</xmax>
			<ymax>426</ymax>
		</bndbox>
	</object>
	<object>
		<name>car</name>
		<pose>Unspecified</pose>
		<truncated>0</truncated>
		<difficult>0</difficult>
		<bndbox>
			<xmin>782</xmin>
			<ymin>366</ymin>
			<xmax>813</xmax>
			<ymax>417</ymax>
		</bndbox>
	</object>
	<object>
		<name>car</name>
		<pose>Unspecified</pose>
		<truncated>0</truncated>
		<difficult>0</difficult>
		<bndbox>
			<xmin>800</xmin>
			<ymin>355</ymin>
			<xmax>858</xmax>
			<ymax>435</ymax>
		</bndbox>
	</object>
	<object>
		<name>car</name>
		<pose>Unspecified</pose>
		<truncated>0</truncated>
		<difficult>0</difficult>
		<bndbox>
			<xmin>836</xmin>
			<ymin>246</ymin>
			<xmax>1165</xmax>
			<ymax>538</ymax>
		</bndbox>
	</object>
	<object>
		<name>car</name>
		<pose>Unspecified</pose>
		<truncated>0</truncated>
		<difficult>0</difficult>
		<bndbox>
			<xmin>1001</xmin>
			<ymin>296</ymin>
			<xmax>1278</xmax>
			<ymax>641</ymax>
		</bndbox>
	</object>
</annotation>
