<?xml version="1.0" ?>
<annotation>
	<folder>bdd100k</folder>
	<filename>13c94581-e10b6cc2.jpg</filename>
	<source>
		<database>voc_bdd</database>
		<annotation>bdd100k</annotation>
		<image>flickr</image>
		<flickrid>NULL</flickrid>
	</source>
	<owner>
		<flickrid>NULL</flickrid>
		<name>lijing</name>
	</owner>
	<size>
		<width>1280</width>
		<height>720</height>
		<depth>3</depth>
	</size>
	<segmented>0</segmented>
	<object>
		<name>car</name>
		<pose>Unspecified</pose>
		<truncated>0</truncated>
		<difficult>0</difficult>
		<bndbox>
			<xmin>621</xmin>
			<ymin>341</ymin>
			<xmax>646</xmax>
			<ymax>374</ymax>
		</bndbox>
	</object>
	<object>
		<name>car</name>
		<pose>Unspecified</pose>
		<truncated>0</truncated>
		<difficult>0</difficult>
		<bndbox>
			<xmin>866</xmin>
			<ymin>332</ymin>
			<xmax>1012</xmax>
			<ymax>430</ymax>
		</bndbox>
	</object>
	<object>
		<name>car</name>
		<pose>Unspecified</pose>
		<truncated>0</truncated>
		<difficult>0</difficult>
		<bndbox>
			<xmin>532</xmin>
			<ymin>342</ymin>
			<xmax>580</xmax>
			<ymax>372</ymax>
		</bndbox>
	</object>
	<object>
		<name>car</name>
		<pose>Unspecified</pose>
		<truncated>0</truncated>
		<difficult>0</difficult>
		<bndbox>
			<xmin>571</xmin>
			<ymin>346</ymin>
			<xmax>636</xmax>
			<ymax>402</ymax>
		</bndbox>
	</object>
	<object>
		<name>car</name>
		<pose>Unspecified</pose>
		<truncated>0</truncated>
		<difficult>0</difficult>
		<bndbox>
			<xmin>485</xmin>
			<ymin>356</ymin>
			<xmax>559</xmax>
			<ymax>407</ymax>
		</bndbox>
	</object>
	<object>
		<name>car</name>
		<pose>Unspecified</pose>
		<truncated>0</truncated>
		<difficult>0</difficult>
		<bndbox>
			<xmin>368</xmin>
			<ymin>367</ymin>
			<xmax>478</xmax>
			<ymax>433</ymax>
		</bndbox>
	</object>
	<object>
		<name>car</name>
		<pose>Unspecified</pose>
		<truncated>0</truncated>
		<difficult>0</difficult>
		<bndbox>
			<xmin>105</xmin>
			<ymin>382</ymin>
			<xmax>170</xmax>
			<ymax>428</ymax>
		</bndbox>
	</object>
	<object>
		<name>car</name>
		<pose>Unspecified</pose>
		<truncated>0</truncated>
		<difficult>0</difficult>
		<bndbox>
			<xmin>131</xmin>
			<ymin>369</ymin>
			<xmax>289</xmax>
			<ymax>438</ymax>
		</bndbox>
	</object>
	<object>
		<name>car</name>
		<pose>Unspecified</pose>
		<truncated>0</truncated>
		<difficult>0</difficult>
		<bndbox>
			<xmin>629</xmin>
			<ymin>299</ymin>
			<xmax>887</xmax>
			<ymax>539</ymax>
		</bndbox>
	</object>
	<object>
		<name>car</name>
		<pose>Unspecified</pose>
		<truncated>0</truncated>
		<difficult>0</difficult>
		<bndbox>
			<xmin>1066</xmin>
			<ymin>311</ymin>
			<xmax>1135</xmax>
			<ymax>356</ymax>
		</bndbox>
	</object>
	<object>
		<name>car</name>
		<pose>Unspecified</pose>
		<truncated>0</truncated>
		<difficult>0</difficult>
		<bndbox>
			<xmin>1109</xmin>
			<ymin>293</ymin>
			<xmax>1278</xmax>
			<ymax>359</ymax>
		</bndbox>
	</object>
	<object>
		<name>car</name>
		<pose>Unspecified</pose>
		<truncated>0</truncated>
		<difficult>0</difficult>
		<bndbox>
			<xmin>1108</xmin>
			<ymin>297</ymin>
			<xmax>1279</xmax>
			<ymax>604</ymax>
		</bndbox>
	</object>
</annotation>
