<?xml version="1.0" ?>
<annotation>
	<folder>bdd100k</folder>
	<filename>45c9e5a8-d577d514.jpg</filename>
	<source>
		<database>voc_bdd</database>
		<annotation>bdd100k</annotation>
		<image>flickr</image>
		<flickrid>NULL</flickrid>
	</source>
	<owner>
		<flickrid>NULL</flickrid>
		<name>lijing</name>
	</owner>
	<size>
		<width>1280</width>
		<height>720</height>
		<depth>3</depth>
	</size>
	<segmented>0</segmented>
	<object>
		<name>car</name>
		<pose>Unspecified</pose>
		<truncated>0</truncated>
		<difficult>0</difficult>
		<bndbox>
			<xmin>325</xmin>
			<ymin>394</ymin>
			<xmax>373</xmax>
			<ymax>433</ymax>
		</bndbox>
	</object>
	<object>
		<name>car</name>
		<pose>Unspecified</pose>
		<truncated>0</truncated>
		<difficult>0</difficult>
		<bndbox>
			<xmin>227</xmin>
			<ymin>400</ymin>
			<xmax>268</xmax>
			<ymax>431</ymax>
		</bndbox>
	</object>
	<object>
		<name>car</name>
		<pose>Unspecified</pose>
		<truncated>0</truncated>
		<difficult>0</difficult>
		<bndbox>
			<xmin>696</xmin>
			<ymin>416</ymin>
			<xmax>784</xmax>
			<ymax>455</ymax>
		</bndbox>
	</object>
	<object>
		<name>car</name>
		<pose>Unspecified</pose>
		<truncated>0</truncated>
		<difficult>0</difficult>
		<bndbox>
			<xmin>815</xmin>
			<ymin>424</ymin>
			<xmax>862</xmax>
			<ymax>459</ymax>
		</bndbox>
	</object>
	<object>
		<name>car</name>
		<pose>Unspecified</pose>
		<truncated>0</truncated>
		<difficult>0</difficult>
		<bndbox>
			<xmin>861</xmin>
			<ymin>426</ymin>
			<xmax>963</xmax>
			<ymax>474</ymax>
		</bndbox>
	</object>
	<object>
		<name>car</name>
		<pose>Unspecified</pose>
		<truncated>0</truncated>
		<difficult>0</difficult>
		<bndbox>
			<xmin>462</xmin>
			<ymin>379</ymin>
			<xmax>643</xmax>
			<ymax>532</ymax>
		</bndbox>
	</object>
</annotation>
