<?xml version="1.0" ?>
<annotation>
	<folder>bdd100k</folder>
	<filename>50b5bf96-45ccbcc6.jpg</filename>
	<source>
		<database>voc_bdd</database>
		<annotation>bdd100k</annotation>
		<image>flickr</image>
		<flickrid>NULL</flickrid>
	</source>
	<owner>
		<flickrid>NULL</flickrid>
		<name>lijing</name>
	</owner>
	<size>
		<width>1280</width>
		<height>720</height>
		<depth>3</depth>
	</size>
	<segmented>0</segmented>
	<object>
		<name>car</name>
		<pose>Unspecified</pose>
		<truncated>0</truncated>
		<difficult>0</difficult>
		<bndbox>
			<xmin>496</xmin>
			<ymin>330</ymin>
			<xmax>532</xmax>
			<ymax>350</ymax>
		</bndbox>
	</object>
	<object>
		<name>car</name>
		<pose>Unspecified</pose>
		<truncated>0</truncated>
		<difficult>0</difficult>
		<bndbox>
			<xmin>475</xmin>
			<ymin>328</ymin>
			<xmax>497</xmax>
			<ymax>345</ymax>
		</bndbox>
	</object>
	<object>
		<name>car</name>
		<pose>Unspecified</pose>
		<truncated>0</truncated>
		<difficult>0</difficult>
		<bndbox>
			<xmin>452</xmin>
			<ymin>330</ymin>
			<xmax>477</xmax>
			<ymax>350</ymax>
		</bndbox>
	</object>
	<object>
		<name>car</name>
		<pose>Unspecified</pose>
		<truncated>0</truncated>
		<difficult>0</difficult>
		<bndbox>
			<xmin>430</xmin>
			<ymin>334</ymin>
			<xmax>461</xmax>
			<ymax>358</ymax>
		</bndbox>
	</object>
	<object>
		<name>car</name>
		<pose>Unspecified</pose>
		<truncated>0</truncated>
		<difficult>0</difficult>
		<bndbox>
			<xmin>410</xmin>
			<ymin>334</ymin>
			<xmax>438</xmax>
			<ymax>358</ymax>
		</bndbox>
	</object>
	<object>
		<name>car</name>
		<pose>Unspecified</pose>
		<truncated>0</truncated>
		<difficult>0</difficult>
		<bndbox>
			<xmin>371</xmin>
			<ymin>331</ymin>
			<xmax>422</xmax>
			<ymax>373</ymax>
		</bndbox>
	</object>
	<object>
		<name>car</name>
		<pose>Unspecified</pose>
		<truncated>0</truncated>
		<difficult>0</difficult>
		<bndbox>
			<xmin>293</xmin>
			<ymin>342</ymin>
			<xmax>352</xmax>
			<ymax>403</ymax>
		</bndbox>
	</object>
	<object>
		<name>car</name>
		<pose>Unspecified</pose>
		<truncated>0</truncated>
		<difficult>0</difficult>
		<bndbox>
			<xmin>173</xmin>
			<ymin>317</ymin>
			<xmax>299</xmax>
			<ymax>422</ymax>
		</bndbox>
	</object>
	<object>
		<name>car</name>
		<pose>Unspecified</pose>
		<truncated>0</truncated>
		<difficult>0</difficult>
		<bndbox>
			<xmin>1</xmin>
			<ymin>344</ymin>
			<xmax>219</xmax>
			<ymax>478</ymax>
		</bndbox>
	</object>
	<object>
		<name>car</name>
		<pose>Unspecified</pose>
		<truncated>0</truncated>
		<difficult>0</difficult>
		<bndbox>
			<xmin>535</xmin>
			<ymin>328</ymin>
			<xmax>555</xmax>
			<ymax>344</ymax>
		</bndbox>
	</object>
	<object>
		<name>car</name>
		<pose>Unspecified</pose>
		<truncated>0</truncated>
		<difficult>0</difficult>
		<bndbox>
			<xmin>549</xmin>
			<ymin>289</ymin>
			<xmax>608</xmax>
			<ymax>352</ymax>
		</bndbox>
	</object>
	<object>
		<name>car</name>
		<pose>Unspecified</pose>
		<truncated>0</truncated>
		<difficult>0</difficult>
		<bndbox>
			<xmin>572</xmin>
			<ymin>331</ymin>
			<xmax>613</xmax>
			<ymax>361</ymax>
		</bndbox>
	</object>
	<object>
		<name>car</name>
		<pose>Unspecified</pose>
		<truncated>0</truncated>
		<difficult>0</difficult>
		<bndbox>
			<xmin>622</xmin>
			<ymin>330</ymin>
			<xmax>688</xmax>
			<ymax>397</ymax>
		</bndbox>
	</object>
	<object>
		<name>car</name>
		<pose>Unspecified</pose>
		<truncated>0</truncated>
		<difficult>0</difficult>
		<bndbox>
			<xmin>652</xmin>
			<ymin>322</ymin>
			<xmax>773</xmax>
			<ymax>423</ymax>
		</bndbox>
	</object>
	<object>
		<name>car</name>
		<pose>Unspecified</pose>
		<truncated>0</truncated>
		<difficult>0</difficult>
		<bndbox>
			<xmin>725</xmin>
			<ymin>311</ymin>
			<xmax>1033</xmax>
			<ymax>490</ymax>
		</bndbox>
	</object>
</annotation>
