<?xml version="1.0" ?>
<annotation>
	<folder>bdd100k</folder>
	<filename>5e7e6383-fbe4f943.jpg</filename>
	<source>
		<database>voc_bdd</database>
		<annotation>bdd100k</annotation>
		<image>flickr</image>
		<flickrid>NULL</flickrid>
	</source>
	<owner>
		<flickrid>NULL</flickrid>
		<name>lijing</name>
	</owner>
	<size>
		<width>1280</width>
		<height>720</height>
		<depth>3</depth>
	</size>
	<segmented>0</segmented>
	<object>
		<name>car</name>
		<pose>Unspecified</pose>
		<truncated>0</truncated>
		<difficult>0</difficult>
		<bndbox>
			<xmin>1</xmin>
			<ymin>327</ymin>
			<xmax>311</xmax>
			<ymax>655</ymax>
		</bndbox>
	</object>
	<object>
		<name>car</name>
		<pose>Unspecified</pose>
		<truncated>0</truncated>
		<difficult>0</difficult>
		<bndbox>
			<xmin>293</xmin>
			<ymin>407</ymin>
			<xmax>437</xmax>
			<ymax>518</ymax>
		</bndbox>
	</object>
	<object>
		<name>car</name>
		<pose>Unspecified</pose>
		<truncated>0</truncated>
		<difficult>0</difficult>
		<bndbox>
			<xmin>392</xmin>
			<ymin>412</ymin>
			<xmax>450</xmax>
			<ymax>472</ymax>
		</bndbox>
	</object>
	<object>
		<name>car</name>
		<pose>Unspecified</pose>
		<truncated>0</truncated>
		<difficult>0</difficult>
		<bndbox>
			<xmin>458</xmin>
			<ymin>432</ymin>
			<xmax>573</xmax>
			<ymax>497</ymax>
		</bndbox>
	</object>
	<object>
		<name>car</name>
		<pose>Unspecified</pose>
		<truncated>0</truncated>
		<difficult>0</difficult>
		<bndbox>
			<xmin>547</xmin>
			<ymin>437</ymin>
			<xmax>581</xmax>
			<ymax>488</ymax>
		</bndbox>
	</object>
	<object>
		<name>car</name>
		<pose>Unspecified</pose>
		<truncated>0</truncated>
		<difficult>0</difficult>
		<bndbox>
			<xmin>615</xmin>
			<ymin>454</ymin>
			<xmax>666</xmax>
			<ymax>491</ymax>
		</bndbox>
	</object>
	<object>
		<name>car</name>
		<pose>Unspecified</pose>
		<truncated>0</truncated>
		<difficult>0</difficult>
		<bndbox>
			<xmin>658</xmin>
			<ymin>425</ymin>
			<xmax>782</xmax>
			<ymax>531</ymax>
		</bndbox>
	</object>
	<object>
		<name>car</name>
		<pose>Unspecified</pose>
		<truncated>0</truncated>
		<difficult>0</difficult>
		<bndbox>
			<xmin>686</xmin>
			<ymin>436</ymin>
			<xmax>922</xmax>
			<ymax>564</ymax>
		</bndbox>
	</object>
	<object>
		<name>car</name>
		<pose>Unspecified</pose>
		<truncated>0</truncated>
		<difficult>0</difficult>
		<bndbox>
			<xmin>576</xmin>
			<ymin>448</ymin>
			<xmax>626</xmax>
			<ymax>487</ymax>
		</bndbox>
	</object>
</annotation>
