<?xml version="1.0" ?>
<annotation>
	<folder>bdd100k</folder>
	<filename>69989f71-68a0609a.jpg</filename>
	<source>
		<database>voc_bdd</database>
		<annotation>bdd100k</annotation>
		<image>flickr</image>
		<flickrid>NULL</flickrid>
	</source>
	<owner>
		<flickrid>NULL</flickrid>
		<name>lijing</name>
	</owner>
	<size>
		<width>1280</width>
		<height>720</height>
		<depth>3</depth>
	</size>
	<segmented>0</segmented>
	<object>
		<name>car</name>
		<pose>Unspecified</pose>
		<truncated>0</truncated>
		<difficult>0</difficult>
		<bndbox>
			<xmin>533</xmin>
			<ymin>300</ymin>
			<xmax>572</xmax>
			<ymax>328</ymax>
		</bndbox>
	</object>
	<object>
		<name>car</name>
		<pose>Unspecified</pose>
		<truncated>0</truncated>
		<difficult>0</difficult>
		<bndbox>
			<xmin>476</xmin>
			<ymin>286</ymin>
			<xmax>540</xmax>
			<ymax>357</ymax>
		</bndbox>
	</object>
	<object>
		<name>car</name>
		<pose>Unspecified</pose>
		<truncated>0</truncated>
		<difficult>0</difficult>
		<bndbox>
			<xmin>243</xmin>
			<ymin>297</ymin>
			<xmax>354</xmax>
			<ymax>369</ymax>
		</bndbox>
	</object>
	<object>
		<name>car</name>
		<pose>Unspecified</pose>
		<truncated>0</truncated>
		<difficult>0</difficult>
		<bndbox>
			<xmin>397</xmin>
			<ymin>288</ymin>
			<xmax>462</xmax>
			<ymax>352</ymax>
		</bndbox>
	</object>
	<object>
		<name>car</name>
		<pose>Unspecified</pose>
		<truncated>0</truncated>
		<difficult>0</difficult>
		<bndbox>
			<xmin>346</xmin>
			<ymin>294</ymin>
			<xmax>395</xmax>
			<ymax>335</ymax>
		</bndbox>
	</object>
	<object>
		<name>car</name>
		<pose>Unspecified</pose>
		<truncated>0</truncated>
		<difficult>0</difficult>
		<bndbox>
			<xmin>2</xmin>
			<ymin>273</ymin>
			<xmax>346</xmax>
			<ymax>590</ymax>
		</bndbox>
	</object>
	<object>
		<name>car</name>
		<pose>Unspecified</pose>
		<truncated>0</truncated>
		<difficult>0</difficult>
		<bndbox>
			<xmin>442</xmin>
			<ymin>323</ymin>
			<xmax>839</xmax>
			<ymax>598</ymax>
		</bndbox>
	</object>
</annotation>
