<?xml version="1.0" ?>
<annotation>
	<folder>bdd100k</folder>
	<filename>97248eab-329f9369.jpg</filename>
	<source>
		<database>voc_bdd</database>
		<annotation>bdd100k</annotation>
		<image>flickr</image>
		<flickrid>NULL</flickrid>
	</source>
	<owner>
		<flickrid>NULL</flickrid>
		<name>lijing</name>
	</owner>
	<size>
		<width>1280</width>
		<height>720</height>
		<depth>3</depth>
	</size>
	<segmented>0</segmented>
	<object>
		<name>car</name>
		<pose>Unspecified</pose>
		<truncated>0</truncated>
		<difficult>0</difficult>
		<bndbox>
			<xmin>110</xmin>
			<ymin>293</ymin>
			<xmax>279</xmax>
			<ymax>372</ymax>
		</bndbox>
	</object>
	<object>
		<name>car</name>
		<pose>Unspecified</pose>
		<truncated>0</truncated>
		<difficult>0</difficult>
		<bndbox>
			<xmin>561</xmin>
			<ymin>311</ymin>
			<xmax>589</xmax>
			<ymax>324</ymax>
		</bndbox>
	</object>
	<object>
		<name>car</name>
		<pose>Unspecified</pose>
		<truncated>0</truncated>
		<difficult>0</difficult>
		<bndbox>
			<xmin>324</xmin>
			<ymin>308</ymin>
			<xmax>377</xmax>
			<ymax>334</ymax>
		</bndbox>
	</object>
	<object>
		<name>car</name>
		<pose>Unspecified</pose>
		<truncated>0</truncated>
		<difficult>0</difficult>
		<bndbox>
			<xmin>0</xmin>
			<ymin>313</ymin>
			<xmax>85</xmax>
			<ymax>364</ymax>
		</bndbox>
	</object>
	<object>
		<name>car</name>
		<pose>Unspecified</pose>
		<truncated>0</truncated>
		<difficult>0</difficult>
		<bndbox>
			<xmin>458</xmin>
			<ymin>311</ymin>
			<xmax>484</xmax>
			<ymax>327</ymax>
		</bndbox>
	</object>
	<object>
		<name>car</name>
		<pose>Unspecified</pose>
		<truncated>0</truncated>
		<difficult>0</difficult>
		<bndbox>
			<xmin>405</xmin>
			<ymin>316</ymin>
			<xmax>448</xmax>
			<ymax>330</ymax>
		</bndbox>
	</object>
	<object>
		<name>car</name>
		<pose>Unspecified</pose>
		<truncated>0</truncated>
		<difficult>0</difficult>
		<bndbox>
			<xmin>649</xmin>
			<ymin>303</ymin>
			<xmax>686</xmax>
			<ymax>326</ymax>
		</bndbox>
	</object>
	<object>
		<name>car</name>
		<pose>Unspecified</pose>
		<truncated>0</truncated>
		<difficult>0</difficult>
		<bndbox>
			<xmin>886</xmin>
			<ymin>277</ymin>
			<xmax>900</xmax>
			<ymax>295</ymax>
		</bndbox>
	</object>
	<object>
		<name>car</name>
		<pose>Unspecified</pose>
		<truncated>0</truncated>
		<difficult>0</difficult>
		<bndbox>
			<xmin>857</xmin>
			<ymin>276</ymin>
			<xmax>881</xmax>
			<ymax>293</ymax>
		</bndbox>
	</object>
	<object>
		<name>car</name>
		<pose>Unspecified</pose>
		<truncated>0</truncated>
		<difficult>0</difficult>
		<bndbox>
			<xmin>834</xmin>
			<ymin>295</ymin>
			<xmax>867</xmax>
			<ymax>313</ymax>
		</bndbox>
	</object>
	<object>
		<name>car</name>
		<pose>Unspecified</pose>
		<truncated>0</truncated>
		<difficult>0</difficult>
		<bndbox>
			<xmin>895</xmin>
			<ymin>283</ymin>
			<xmax>926</xmax>
			<ymax>308</ymax>
		</bndbox>
	</object>
	<object>
		<name>car</name>
		<pose>Unspecified</pose>
		<truncated>0</truncated>
		<difficult>0</difficult>
		<bndbox>
			<xmin>786</xmin>
			<ymin>315</ymin>
			<xmax>841</xmax>
			<ymax>371</ymax>
		</bndbox>
	</object>
	<object>
		<name>car</name>
		<pose>Unspecified</pose>
		<truncated>0</truncated>
		<difficult>0</difficult>
		<bndbox>
			<xmin>969</xmin>
			<ymin>149</ymin>
			<xmax>1277</xmax>
			<ymax>609</ymax>
		</bndbox>
	</object>
	<object>
		<name>car</name>
		<pose>Unspecified</pose>
		<truncated>0</truncated>
		<difficult>0</difficult>
		<bndbox>
			<xmin>688</xmin>
			<ymin>312</ymin>
			<xmax>763</xmax>
			<ymax>373</ymax>
		</bndbox>
	</object>
	<object>
		<name>car</name>
		<pose>Unspecified</pose>
		<truncated>0</truncated>
		<difficult>0</difficult>
		<bndbox>
			<xmin>809</xmin>
			<ymin>308</ymin>
			<xmax>951</xmax>
			<ymax>409</ymax>
		</bndbox>
	</object>
	<object>
		<name>car</name>
		<pose>Unspecified</pose>
		<truncated>0</truncated>
		<difficult>0</difficult>
		<bndbox>
			<xmin>602</xmin>
			<ymin>313</ymin>
			<xmax>625</xmax>
			<ymax>323</ymax>
		</bndbox>
	</object>
</annotation>
