<?xml version="1.0" ?>
<annotation>
	<folder>bdd100k</folder>
	<filename>ab5bfde7-31f29ba3.jpg</filename>
	<source>
		<database>voc_bdd</database>
		<annotation>bdd100k</annotation>
		<image>flickr</image>
		<flickrid>NULL</flickrid>
	</source>
	<owner>
		<flickrid>NULL</flickrid>
		<name>lijing</name>
	</owner>
	<size>
		<width>1280</width>
		<height>720</height>
		<depth>3</depth>
	</size>
	<segmented>0</segmented>
	<object>
		<name>car</name>
		<pose>Unspecified</pose>
		<truncated>0</truncated>
		<difficult>0</difficult>
		<bndbox>
			<xmin>522</xmin>
			<ymin>192</ymin>
			<xmax>604</xmax>
			<ymax>287</ymax>
		</bndbox>
	</object>
	<object>
		<name>car</name>
		<pose>Unspecified</pose>
		<truncated>0</truncated>
		<difficult>0</difficult>
		<bndbox>
			<xmin>484</xmin>
			<ymin>236</ymin>
			<xmax>526</xmax>
			<ymax>282</ymax>
		</bndbox>
	</object>
	<object>
		<name>car</name>
		<pose>Unspecified</pose>
		<truncated>0</truncated>
		<difficult>0</difficult>
		<bndbox>
			<xmin>436</xmin>
			<ymin>232</ymin>
			<xmax>485</xmax>
			<ymax>277</ymax>
		</bndbox>
	</object>
	<object>
		<name>car</name>
		<pose>Unspecified</pose>
		<truncated>0</truncated>
		<difficult>0</difficult>
		<bndbox>
			<xmin>340</xmin>
			<ymin>225</ymin>
			<xmax>461</xmax>
			<ymax>307</ymax>
		</bndbox>
	</object>
	<object>
		<name>car</name>
		<pose>Unspecified</pose>
		<truncated>0</truncated>
		<difficult>0</difficult>
		<bndbox>
			<xmin>764</xmin>
			<ymin>228</ymin>
			<xmax>862</xmax>
			<ymax>303</ymax>
		</bndbox>
	</object>
	<object>
		<name>car</name>
		<pose>Unspecified</pose>
		<truncated>0</truncated>
		<difficult>0</difficult>
		<bndbox>
			<xmin>703</xmin>
			<ymin>237</ymin>
			<xmax>716</xmax>
			<ymax>273</ymax>
		</bndbox>
	</object>
	<object>
		<name>car</name>
		<pose>Unspecified</pose>
		<truncated>0</truncated>
		<difficult>0</difficult>
		<bndbox>
			<xmin>599</xmin>
			<ymin>198</ymin>
			<xmax>710</xmax>
			<ymax>319</ymax>
		</bndbox>
	</object>
	<object>
		<name>car</name>
		<pose>Unspecified</pose>
		<truncated>0</truncated>
		<difficult>0</difficult>
		<bndbox>
			<xmin>821</xmin>
			<ymin>181</ymin>
			<xmax>1150</xmax>
			<ymax>387</ymax>
		</bndbox>
	</object>
</annotation>
