<?xml version="1.0" ?>
<annotation>
	<folder>bdd100k</folder>
	<filename>c540d300-d60d1a91.jpg</filename>
	<source>
		<database>voc_bdd</database>
		<annotation>bdd100k</annotation>
		<image>flickr</image>
		<flickrid>NULL</flickrid>
	</source>
	<owner>
		<flickrid>NULL</flickrid>
		<name>lijing</name>
	</owner>
	<size>
		<width>1280</width>
		<height>720</height>
		<depth>3</depth>
	</size>
	<segmented>0</segmented>
	<object>
		<name>car</name>
		<pose>Unspecified</pose>
		<truncated>0</truncated>
		<difficult>0</difficult>
		<bndbox>
			<xmin>1071</xmin>
			<ymin>322</ymin>
			<xmax>1279</xmax>
			<ymax>632</ymax>
		</bndbox>
	</object>
	<object>
		<name>car</name>
		<pose>Unspecified</pose>
		<truncated>0</truncated>
		<difficult>0</difficult>
		<bndbox>
			<xmin>838</xmin>
			<ymin>356</ymin>
			<xmax>933</xmax>
			<ymax>426</ymax>
		</bndbox>
	</object>
	<object>
		<name>car</name>
		<pose>Unspecified</pose>
		<truncated>0</truncated>
		<difficult>0</difficult>
		<bndbox>
			<xmin>811</xmin>
			<ymin>358</ymin>
			<xmax>855</xmax>
			<ymax>401</ymax>
		</bndbox>
	</object>
	<object>
		<name>car</name>
		<pose>Unspecified</pose>
		<truncated>0</truncated>
		<difficult>0</difficult>
		<bndbox>
			<xmin>794</xmin>
			<ymin>353</ymin>
			<xmax>826</xmax>
			<ymax>395</ymax>
		</bndbox>
	</object>
	<object>
		<name>car</name>
		<pose>Unspecified</pose>
		<truncated>0</truncated>
		<difficult>0</difficult>
		<bndbox>
			<xmin>769</xmin>
			<ymin>354</ymin>
			<xmax>792</xmax>
			<ymax>370</ymax>
		</bndbox>
	</object>
	<object>
		<name>car</name>
		<pose>Unspecified</pose>
		<truncated>0</truncated>
		<difficult>0</difficult>
		<bndbox>
			<xmin>545</xmin>
			<ymin>348</ymin>
			<xmax>581</xmax>
			<ymax>388</ymax>
		</bndbox>
	</object>
	<object>
		<name>car</name>
		<pose>Unspecified</pose>
		<truncated>0</truncated>
		<difficult>0</difficult>
		<bndbox>
			<xmin>482</xmin>
			<ymin>349</ymin>
			<xmax>553</xmax>
			<ymax>384</ymax>
		</bndbox>
	</object>
	<object>
		<name>car</name>
		<pose>Unspecified</pose>
		<truncated>0</truncated>
		<difficult>0</difficult>
		<bndbox>
			<xmin>256</xmin>
			<ymin>334</ymin>
			<xmax>362</xmax>
			<ymax>380</ymax>
		</bndbox>
	</object>
	<object>
		<name>car</name>
		<pose>Unspecified</pose>
		<truncated>0</truncated>
		<difficult>0</difficult>
		<bndbox>
			<xmin>388</xmin>
			<ymin>343</ymin>
			<xmax>490</xmax>
			<ymax>395</ymax>
		</bndbox>
	</object>
	<object>
		<name>car</name>
		<pose>Unspecified</pose>
		<truncated>0</truncated>
		<difficult>0</difficult>
		<bndbox>
			<xmin>694</xmin>
			<ymin>350</ymin>
			<xmax>742</xmax>
			<ymax>372</ymax>
		</bndbox>
	</object>
</annotation>
